setup.cfg
setup.py
simple_telegrambot.egg-info/PKG-INFO
simple_telegrambot.egg-info/SOURCES.txt
simple_telegrambot.egg-info/dependency_links.txt
simple_telegrambot.egg-info/requires.txt
simple_telegrambot.egg-info/top_level.txt
simpletelegrambot/__init__.py
simpletelegrambot/telegrambot.py