Metadata-Version: 1.1
Name: simple-telegrambot
Version: 1.0.2
Summary: A simple Telegram bot which sends and receive messages
Home-page: https://github.com/umahmood/simple-telegrambot
Author: Usman Mahmood
Author-email: um@blackhole.com
License: UNKNOWN
Download-URL: https://github.com/umahmood/simple-telegrambot/archive/1.0.2.tar.gz
Keywords: bot,telegram
Platform: UNKNOWN
